resummation/__init__.py
resummation/__version__.py
resummation/flamingofunctions.py
resummation/resummation.py
resummation/fitparams/params_fret_vs_fbc_L2p8m9_0058_ALL_bfixed_err_selectm500_noreject_highres_HBT_ownmass.json
resummation/fitparams/params_fret_vs_fbc_L2p8m9_0068_ALL_bfixed_err_selectm500_noreject_highres_HBT_ownmass.json
resummation/fitparams/params_fret_vs_fbc_L2p8m9_0078_ALL_bfixed_err_selectm500_noreject_highres_HBT_ownmass.json
resummation/fractions/fbar_HYDRO_ADIABATIC_L1000N1800_0057_HBT.json
resummation/fractions/fbar_HYDRO_ADIABATIC_L1000N1800_0067_HBT.json
resummation/fractions/fbar_HYDRO_ADIABATIC_L1000N1800_0077_HBT.json
resummation/fractions/fbar_HYDRO_FIDUCIAL_L1000N1800_0057_HBT.json
resummation/fractions/fbar_HYDRO_FIDUCIAL_L1000N1800_0067_HBT.json
resummation/fractions/fbar_HYDRO_FIDUCIAL_L1000N1800_0077_HBT.json
resummation/fractions/fbar_HYDRO_FIDUCIAL_L1000N3600_0078_HBT.json
resummation/fractions/fbar_HYDRO_FIDUCIAL_L2800N5040_0078_HBT.json
resummation/fractions/fbar_HYDRO_JETS_published_L1000N1800_0057_HBT.json
resummation/fractions/fbar_HYDRO_JETS_published_L1000N1800_0067_HBT.json
resummation/fractions/fbar_HYDRO_JETS_published_L1000N1800_0077_HBT.json
resummation/fractions/fbar_HYDRO_LOW_SIGMA8_L1000N1800_0057_HBT.json
resummation/fractions/fbar_HYDRO_LOW_SIGMA8_L1000N1800_0067_HBT.json
resummation/fractions/fbar_HYDRO_LOW_SIGMA8_L1000N1800_0077_HBT.json
resummation/fractions/fbar_HYDRO_LOW_SIGMA8_STRONGEST_AGN_L1000N1800_0057_HBT.json
resummation/fractions/fbar_HYDRO_LOW_SIGMA8_STRONGEST_AGN_L1000N1800_0067_HBT.json
resummation/fractions/fbar_HYDRO_LOW_SIGMA8_STRONGEST_AGN_L1000N1800_0077_HBT.json
resummation/fractions/fbar_HYDRO_PLANCK_L1000N1800_0057_HBT.json
resummation/fractions/fbar_HYDRO_PLANCK_L1000N1800_0067_HBT.json
resummation/fractions/fbar_HYDRO_PLANCK_L1000N1800_0077_HBT.json
resummation/fractions/fbar_HYDRO_PLANCK_LARGER_NU_FIXED_L1000N1800_0057_HBT.json
resummation-1.0.1.dist-info/licenses/LICENSE
resummation-1.0.1.dist-info/WHEEL
resummation-1.0.1.dist-info/METADATA
resummation-1.0.1.dist-info/RECORD
