Metadata-Version: 2.4
Name: resummation
Version: 1.0.1
Summary: Resummation model for computing suppression signals from baryon fractions.
Author-email: Marcel van Daalen <daalen@strw.leidenuniv.nl>
License-Expression: GPL-3.0-or-later
License-File: LICENSE
